LICENSE
README.rst
setup.cfg
setup.py
pyvcsshark/__init__.py
pyvcsshark/config.py
pyvcsshark/loggerConfiguration.json
pyvcsshark/main.py
pyvcsshark/utils.py
pyvcsshark/datastores/__init__.py
pyvcsshark/datastores/basestore.py
pyvcsshark/datastores/mongostore.py
pyvcsshark/datastores/mysqlstore.py
pyvcsshark/parser/__init__.py
pyvcsshark/parser/baseparser.py
pyvcsshark/parser/gitparser.py
pyvcsshark/parser/models.py
pyvcsshark/parser/svnparser.py
tests/__init__.py
tests/datastoremock.py
tests/test_gitparser.py
tests/test_mongostore.py
vcsSHARK.egg-info/PKG-INFO
vcsSHARK.egg-info/SOURCES.txt
vcsSHARK.egg-info/dependency_links.txt
vcsSHARK.egg-info/entry_points.txt
vcsSHARK.egg-info/not-zip-safe
vcsSHARK.egg-info/requires.txt
vcsSHARK.egg-info/top_level.txt