Metadata-Version: 2.1
Name: vcsSHARK
Version: 2.1.1
Summary: vcsSHARK is a tool to analyze source code repositories
Home-page: https://github.com/smartshark/vcsSHARK
Author: Fabian Trautsch
Author-email: trautsch@cs.uni-goettingen.de
License: UNKNOWN
Download-URL: https://github.com/smartshark/vcsSHARK/zipball/master
Platform: UNKNOWN
Classifier: Programming Language :: Python :: 3
Classifier: Development Status :: 4 - Beta
Classifier: Environment :: Console
Classifier: Intended Audience :: Developers
Classifier: License :: OSI Approved :: Apache Software License
Classifier: Operating System :: POSIX :: Linux
Classifier: Topic :: Software Development :: Libraries :: Python Modules
License-File: LICENSE
